zeekshipper/__init__.py
zeekshipper/zeeker.py
zeekshipper-0.1.0.dist-info/entry_points.txt
zeekshipper-0.1.0.dist-info/WHEEL
zeekshipper-0.1.0.dist-info/METADATA
zeekshipper-0.1.0.dist-info/RECORD
